fastVAR.py
setup.py
fastVAR.egg-info/PKG-INFO
fastVAR.egg-info/SOURCES.txt
fastVAR.egg-info/dependency_links.txt
fastVAR.egg-info/requires.txt
fastVAR.egg-info/top_level.txt