Metadata-Version: 1.0
Name: fastVAR
Version: 1.0
Summary: Vector AutoRegressive model for time series data.  Requires numpy.
Home-page: http://www.stanford.edu/~jeffwong
Author: Jeffrey Wong
Author-email: jeff.ct.wong@stanford.edu
License: UNKNOWN
Platform: UNKNOWN
